{
  "CompanyName": "LESCO",
  "MetaDataForDevelopment": "",
  "billerUIConversion": {
    "fieldsList": [
      {
        "BillingMonthDropDown": {
          "id": 1,
          "value": "",
          "label": "Billing Month",
          "list": "",
          "isDisabled": false,
          "isVisible": true,
          "isMandatory": true,
          "maxlength": 20,
          "mask": "",
          "eventType": "onChange",
          "type": "dropDown",
          "itemValue":"billingMonth",
          "sequenceNO":1
        },
        "AmountAfterDueDateTextBox": {
          "id": 2,
          "value": "",
          "dataType": "numericDecimal",
          "isMandatory": false,
          "label": "Amount After Due Date",
          "maxlength": 20,
          "mask": "",
          "isDisabled": true,
          "isVisible": true,
          "eventType": "onBlur",
          "type": "textBox",
          "itemValue":"amountAfterDueDate",
          "textAlign":"right",
          "sequenceNO":2
        },
        "ConsumerNumberTextBox": {
          "id": 1,
          "value": "",
          "dataType": "alphaNumericSpecial",
          "isMandatory": false,
          "label": "Consumer No-LESCO",
          "maxlength": 20,
          "mask": "",
          "isDisabled": false,
          "isVisible": true,
          "eventType": "onBlur",
          "type": "textBox",
          "itemValue": "item5",
          "sequenceNO":3
        },
        "CustomerNameTextBox": {
          "id": 2,
          "value": "",
          "dataType": "alphaNumericSpecial",
          "isMandatory": false,
          "label": "Consumer Name",
          "maxlength": 60,
          "mask": "",
          "isDisabled": true,
          "isVisible": true,
          "eventType": "onBlur",
          "type": "textBox",
          "itemValue":"customerName",
          "sequenceNO":4
        },
        "BillAmountToBePaidTextBox": {
          "id": 1,
          "value": "",
          "dataType": "numericDecimal",
          "isMandatory": false,
          "label": "Billing Amount",
          "maxlength": 20,
          "mask": "",
          "isDisabled": true,
          "isVisible": true,
          "eventType": "onBlur",
          "type": "textBox",
          "textAlign":"right",
          "sequenceNO":5
        },
        "CustomerIdTextBox": {
          "id": 2,
          "value": "",
          "dataType": "alphaNumericSpecial",
          "isMandatory": false,
          "label": "Consumer Id",
          "maxlength": 20,
          "mask": "",
          "isDisabled": true,
          "isVisible": true,
          "eventType": "onBlur",
          "type": "textBox",
          "itemValue":"custID",
          "sequenceNO":6
        },
        "WithinDueDateAmountTextBox": {
          "id": 1,
          "value": "",
          "dataType": "numericDecimal",
          "isMandatory": false,
          "label": "Amount Within Due Date",
          "maxlength": 20,
          "mask": "",
          "isDisabled": true,
          "isVisible": true,
          "eventType": "onBlur",
          "type": "textBox",
          "itemValue":"amountWithinDueDate",
          "textAlign":"right",
          "sequenceNO":7
        },
        "AddressTextBox": {
          "id": 2,
          "value": "",
          "dataType": "alphaNumericSpecial",
          "isMandatory": false,
          "label": "Address",
          "maxlength": 20,
          "mask": "",
          "isDisabled": true,
          "isVisible": true,
          "eventType": "onBlur",
          "type": "textBox",
          "itemValue":"address",
          "sequenceNO":8
        },
        "DueDateTextBox": {
          "id": 1,
          "value": "",
          "dataType": "alphaNumericSpecial",
          "isMandatory": false,
          "label": "Due Date",
          "maxlength": 20,
          "mask": "##/##/####",
          "isDisabled": true,
          "isVisible": true,
          "eventType": "onBlur",
          "type": "textBox",
          "itemValue":"dueDate",
          "sequenceNO":9
        },
        "FetchDetailInformationButton": {
          "id": 2,
          "sequenceNO":10,
          "isDisabled": false,
          "isVisible": true
        },
        "PostButton": {
          "isDisabled": true
        }
      }
    ]
  },
  "billerMatrixConversion": [
    {
      "header": {
        "loginBranch": "",
        "loginUserId": "",
        "loginUserBatch": "",
        "loginUserIp": "",
        "activityCode": "UBPFTRCV",
        "subActivityCode": "", 
        "loginBranchDate": "",
        "currencyCode": "586"
      },
      "transactionDto": [
        {
          "billDetail": {
            "companyId": "",
            "companyName": "",
            "barCode": "",
            "paymentMode": "CHEQUE", 
            "companyBranchCode": "",
            "companyAccountType": "",
            "companyCustomerNumber": "",
            "companyRunNumber": "",
            "companyCheckDigit": "",
            "accountName": "",
            "debitBranchCode": "",
            "debitAccountType": "",
            "debitCustomerNumber": "",
            "debitRunNumber": "",
            "debitCheckDigit": "",
            "chequeNumber": "",
            "chequeAmount": "",
            "totalBills": 1,
            "slipNumber": "ConsumerNumberTextBox",
            "customerName": "CustomerNameTextBox",
            "validityDate": "",
            "billingMonth": "BillingMonthDropDown",
            "dueDate": "DueDateTextBox",
            "afterDueDate": "",
            "billingAmount": "BillAmountToBePaidTextBox",
            "afterDueDateBillingAmount": "AmountAfterDueDateTextBox",
            "transactionAmount": "BillAmountToBePaidTextBox",
            "contractAccount": "",
            "customerId": "CustomerIdTextBox",
            "dealerCode": "",
            "dealerName": "",
            "productCode": "",
            "productName": "",
            "totalCharges": "",
            "bankShares": "",
            "totalAmount": "",
            "address": "AddressTextBox",
            "extra1": "companyCode",
            "extra2": "ConsumerNumberTextBox",
            "extra3": "companyAbr",
            "extra4": "",
            "extra5": "",
            "extra6": "",
            "extra7": "",
            "extra8": "",
            "extra9": "",
            "extra10": "",
            "extra11": "NarrationTextBox",
            "extra12": "",
            "extra13": "",
            "extra14": "",
            "extra15": "",
            "extra16": "",
            "extra17": "",
            "extra18": "",
            "extra19": "",
            "extra20": ""
          },
            "billingCompanyApi": {
              "metadata": {
                "source": {
                  "identifier": "OBS_CC_UC7_FT_FT"
                },
                "destination": {
                  "identifier": "LahoreElectricSupplyCompanyApiPaymentRequest"
                },
                "type": "realtime"
              },
              "data": {
                "externalServiceApiRequest": {
                  "companyId": "LESCO_PAY",
                  "companyReferenceNumber": "LESCO0001",
                  "invoiceNumber": "",
                  "customerReferenceNumber": "ConsumerNumberTextBox",
                  "transactionAmount": "BillAmountToBePaidTextBox",
                  "financialInstitutionMnemonic": "",
                  "transactionIdentifier": "loginBranchDateTimeFromFrontEnd",
                  "customerAccountNumber": "",
                  "purchaseOrderAmount": "amountAfterDueDate",
                  "contactNumber": "",
                  "messageOrigniationAdviseNumber": "",
                  "customerName": "CustomerNameTextBox",
                  "postingBy": "loginUserId",
                  "uniqueIdentity": "",
                  "branchNumber": "lescoBranchCode",
                  "branchDescription": "lescoBranchName",
                  "transactionDateTime": "transactionDateTime",
                  "transactionDate": "transactionDate",
                  "transactionTime":"transactionDateTime",
                  "transactionAuthorizationId": "",
                  "customerPaymentChoice": "U",
                  "transactionEffectiveDate": "transactionEffectiveDate",
                  "iso4217": "",
                  "currencyTradeRate": "",
                  "extra_1": "",
                  "extra_2": "",
                  "extra_3": "cardType",
                  "extra_4": "13",
                  "extra_5": "custID",
                  "extra_6": "",
                  "extra_8": "",
                  "extra_9": "",
                  "extra_10": "",
                  "extra_11": "",
                  "extra_12": "",
                  "extra_13": "",
                  "extra_14": "",
                  "extra_15": ""
                }
              }
            }
          
        }
      ]
    }
  ],
  "API":{
    "isInquiry":true,
    "isPayment":true,
     "apiInquiryRequestDto":{
      "metaData": {
        "source": {
          "identifier": "OBS_CC_UC7_FT_FT"
        },
        "destination": {
          "identifier": "LahoreElectricSupplyCompanyApiInquiryRequest"
        },
        "type": "realtime"
      },
      "data": {
        "externalServiceApiRequest": {
          "companyId": "LESCO_INQ",
          "companyReferenceNumber": "LESCO0001",
          "invoiceNumber": "ConsumerNumberTextBox",
          "customerReferenceNumber": "ConsumerNumberTextBox",
          "transactionAmount": "",
          "financialInstitutionMnemonic": "",
          "transactionIdentifier": "loginBranchDateTimeFromFrontEnd",
          "transactionDateTime": "loginBranchDateTimeFromFrontEnd",
          "extra_1": "",
          "extra_2": "",
          "extra_3": "",
          "extra_4": "",
          "extra_5": "",
          "extra_6": "",
          "extra_7": "",
          "extra_8": "",
          "extra_9": "",
          "extra_10": "",
          "extra_11": "",
          "extra_12": "",
          "extra_13": "",
          "extra_14": "",
          "extra_15": ""
        }
      }
    },
    "RequiredFieldsBeforeInquiry":{
      "fieldsList":[
        "ConsumerNumberTextBox"
      ]
    }
    
  }
}
